<tv generator-info-url="https://github.com/amazeyourself"><channel id="RUNNTV_LIVECHANNEL_2"><display-name>Cineshorts Premiere</display-name><icon src="https://image.airtel.tv/grandslam/content/2025_05_07/CineshortsLogo-960X540.png" /><lcn>2</lcn></channel><programme channel="RUNNTV_LIVECHANNEL_2" start="20260717000000 +0000" stop="20260719000000 +0000" catchup-id="RUNNTV_PROGRAM_2"><title>Cineshorts Premiere</title><desc /><date>20260717</date><icon src="https://xstreamcp-assets-msp.streamready.in/assets/RUNNTV/LIVECHANNEL/67ed3b4b9555833db945e389/images/LANDSCAPE_169/1fd1e8e4-7886-469f-b16d-8809ee661352.png" /></programme><channel id="RUNNTV_LIVECHANNEL_4"><display-name>Pocket Films</display-name><icon src="https://image.airtel.tv/grandslam/content/2025_05_07/PocketFilmsLogo-960X540.png" /><lcn>4</lcn></channel><programme channel="RUNNTV_LIVECHANNEL_4" start="20260717000000 +0000" stop="20260719000000 +0000" catchup-id="RUNNTV_PROGRAM_4"><title>Pocket Films</title><desc /><date>20260717</date><icon src="https://xstreamcp-assets-msp.streamready.in/assets/RUNNTV/LIVECHANNEL/67ed3b4b9555833db945e388/images/LANDSCAPE_169/1a68c432-a3a5-4ed2-95fc-704837122d60.png" /></programme><channel id="RUNNTV_LIVECHANNEL_6"><display-name>Terribly Tiny Tales</display-name><icon src="https://image.airtel.tv/grandslam/content/2025_05_07/ttt-LOGO-960X540.png" /><lcn>6</lcn></channel><programme channel="RUNNTV_LIVECHANNEL_6" start="20260717000000 +0000" stop="20260719000000 +0000" catchup-id="RUNNTV_PROGRAM_6"><title>Terribly Tiny Tales</title><desc /><date>20260717</date><icon src="https://xstreamcp-assets-msp.streamready.in/assets/RUNNTV/LIVECHANNEL/67ed3b4a9555833db945e386/images/LANDSCAPE_169/c84a08f7-2ece-4e66-8c2b-6f1594676add.png" /></programme><channel id="RUNNTV_LIVECHANNEL_7"><display-name>Runn Action</display-name><icon src="https://image.airtel.tv/grandslam/content/2025_05_07/R_Action-960X540.png" /><lcn>7</lcn></channel><programme channel="RUNNTV_LIVECHANNEL_7" start="20260717120142 +0000" stop="20260717135407 +0000" catchup-id="RUNNTV_PROGRAM_7_1784289702109_1784296447109"><title>The Catcher Was A Spy</title><desc>With an ensemble cast, this gripping, espionage thriller brings to life the true story of Moe Berg a World War II spy. His mission: go behind enemy lines in Europe to assassinate the Nazi's chief nuclear scientist before the Germans develop an atomic bomb. Berg must rely on his steel-trap intellect in a high-stakes game of cat and mouse - with the fate of the world hanging in the balance.</desc><date>20260717</date><icon src="https://xstreamcp-assets-msp.streamready.in/assets/RUNNTV/PROGRAM/6a5a1b99b0f02f4dbdefba2c/images/LANDSCAPE_169/a886df06-7b55-4873-bc23-6b9215c02b13.png" /></programme><programme channel="RUNNTV_LIVECHANNEL_7" start="20260717135407 +0000" stop="20260717154111 +0000" catchup-id="RUNNTV_PROGRAM_7_1784296447109_1784302871109"><title>Haywire</title><desc>From Academy Award-winning director Steven Soderbergh of Ocean&#8217;s 11, 12 &amp; 13 comes HAYWIRE. A Female Assassin covert operative is hired to various global missions to perform jobs which governments can't authorize. When the operation goes awry, she needs to use all of her skills &amp; tricks to escape an international manhunt and eliminate the last remaining link of the conspiracy against her.</desc><date>20260717</date><icon src="https://xstreamcp-assets-msp.streamready.in/assets/RUNNTV/PROGRAM/6a5a1b99b0f02f4dbdefba2f/images/LANDSCAPE_169/fb23382f-d8e4-4fb5-be4f-516af6136659.png" /></programme><programme channel="RUNNTV_LIVECHANNEL_7" start="20260717154111 +0000" stop="20260717173153 +0000" catchup-id="RUNNTV_PROGRAM_7_1784302871109_1784309513109"><title>Redline</title><desc>Redline is an auto/action thriller that features an extensive exotic car collection Phantom Rolls Royce, Lamborghini Murcielago, Enzo Ferrari, Ferrari F430, Ferrari Scaglietti and two Mercedes SLR McLaren AMGs. The film follows a gorgeous young automobile fanaticize driver who becomes part of illegal drag racing competitions organized by exotic car fanatics.</desc><date>20260717</date><icon src="https://xstreamcp-assets-msp.streamready.in/assets/RUNNTV/PROGRAM/6a5a1b9ab0f02f4dbdefba32/images/LANDSCAPE_169/50382a09-975c-415c-9161-5883d0a2cccd.png" /></programme><programme channel="RUNNTV_LIVECHANNEL_7" start="20260717173153 +0000" stop="20260717194459 +0000" catchup-id="RUNNTV_PROGRAM_7_1784309513109_1784317499109"><title>Lawless</title><desc>We control the fear, you understand? Without the fear, we are all good as dead.&#8217; The notorious gangster Al Capone observed that &#8220;Prohibition has made nothing but trouble,&#8221; and &#8220;I am like any other man. All I do is supply a demand.&#8221; Acclaimed director delivers a thrillingly vivid slice of American outlaw history in his epic gangster tale, LAWLESS. LAWLESS is the true story of the infamous Bondurant Brothers: three bootlegging siblings who made a run for the American Dream in Prohibition-era Virginia. The film gathers an ensemble of gifted, dynamic new-generation stars &#8211; Tom Hardy, Shia LaBeouf, Jessica Chastain, Jason Clarke, Mia Wasikowska, Dane DeHaan &#8211; alongside two of the finest actors of their generations, Guy Pearce and Gary Oldman. A riveting, intense story of Crime and Corruption, Loyalty and Love, Brutality and Tenderness, LAWLESS is a rich addition to the American Gangster Canon.</desc><date>20260717</date><icon src="https://xstreamcp-assets-msp.streamready.in/assets/RUNNTV/PROGRAM/6a5a1b9ab0f02f4dbdefba37/images/LANDSCAPE_169/5b722019-dcbf-4890-99d3-427e4d9b6286.png" /></programme><programme channel="RUNNTV_LIVECHANNEL_7" start="20260717194459 +0000" stop="20260717213145 +0000" catchup-id="RUNNTV_PROGRAM_7_1784317499109_1784323905109"><title>Tekken: Kazuya's Revenge</title><desc>Suffering from amnesia, a young man trying to discover his true identity is kidnapped by an underground crime organization and turned into a ruthless assassin</desc><date>20260717</date><icon src="https://xstreamcp-assets-msp.streamready.in/assets/RUNNTV/PROGRAM/6a5a1b9ab0f02f4dbdefba3a/images/LANDSCAPE_169/7a62c1ff-6056-4155-a026-104e1c5045c8.png" /></programme><programme channel="RUNNTV_LIVECHANNEL_7" start="20260717213145 +0000" stop="20260717232310 +0000" catchup-id="RUNNTV_PROGRAM_7_1784323905109_1784330590109"><title>Spytime</title><desc>Anacleto, a former secret agent, is forced to come out of retirement and protect his son, Adolfo, when his arch-enemy, Vazquez, breaks out of prison and targets him</desc><date>20260717</date><icon src="https://xstreamcp-assets-msp.streamready.in/assets/RUNNTV/PROGRAM/6a5a1b9ab0f02f4dbdefba3e/images/LANDSCAPE_169/dd67a82f-3bbc-4415-80be-a5c3b164bfbd.png" /></programme><programme channel="RUNNTV_LIVECHANNEL_7" start="20260717232310 +0000" stop="20260718011802 +0000" catchup-id="RUNNTV_PROGRAM_7_1784330590109_1784337482109"><title>Universal Soldier: Regeneration</title><desc>Terrorists kidnap the Russian Prime Minister's two kids, take Chernobyl Nuclear Power Plant and threaten to blow up a reactor. Four Universal Soldiers go in but are no match to a Next Generation UniSol. The world's only hope is to reactivate decommissioned Universal Soldier Luc Deveraux.</desc><date>20260717</date><icon src="https://xstreamcp-assets-msp.streamready.in/assets/RUNNTV/PROGRAM/6a5a1b9bb0f02f4dbdefba42/images/LANDSCAPE_169/8840830c-584e-4d42-972c-48bae16023c5.png" /></programme><programme channel="RUNNTV_LIVECHANNEL_7" start="20260718011802 +0000" stop="20260718030753 +0000" catchup-id="RUNNTV_PROGRAM_7_1784337482109_1784344073109"><title>Out Of Death</title><desc>From the producers of The Irishman &amp; Lone Survivor comes this thrilling story of Jack Harris (Bruce Willis) who must tap into his killer instincts to survive the wilderness and the human predators as he tries to help a woman who witnesses a crime and finds herself running from a rural mountain town's corrupt police department after she took a video of police killing a drug dealer.</desc><date>20260718</date><icon src="https://xstreamcp-assets-msp.streamready.in/assets/RUNNTV/PROGRAM/6a5a1b9bb0f02f4dbdefba45/images/LANDSCAPE_169/ddf52333-1031-4ef2-a71f-cc9584b9b587.png" /></programme><programme channel="RUNNTV_LIVECHANNEL_7" start="20260718030753 +0000" stop="20260718044258 +0000" catchup-id="RUNNTV_PROGRAM_7_1784344073109_1784349778109"><title>Poseidon Rex</title><desc>While searching for lost treasure, deep sea divers unleash a monster that causes havoc and destruction not only in sea but also on land.</desc><date>20260718</date><icon src="https://xstreamcp-assets-msp.streamready.in/assets/RUNNTV/PROGRAM/6a5a1b9bb0f02f4dbdefba48/images/LANDSCAPE_169/302b74c0-9614-4c74-8740-366fa010d1cf.png" /></programme><programme channel="RUNNTV_LIVECHANNEL_7" start="20260718044258 +0000" stop="20260718061037 +0000" catchup-id="RUNNTV_PROGRAM_7_1784349778109_1784355037109"><title>Wrecker</title><desc>Two beautiful young women taking a trip through the countryside, are terrorized by an unknown driver trying to run them down in a heavy duty tow truck.</desc><date>20260718</date><icon src="https://xstreamcp-assets-msp.streamready.in/assets/RUNNTV/PROGRAM/6a5a1b9bb0f02f4dbdefba4a/images/LANDSCAPE_169/8efd5fe9-1166-4225-a3ca-82f63ef5d931.png" /></programme><programme channel="RUNNTV_LIVECHANNEL_7" start="20260718061037 +0000" stop="20260718080302 +0000" catchup-id="RUNNTV_PROGRAM_7_1784355037109_1784361782109"><title>The Catcher Was A Spy</title><desc>With an ensemble cast, this gripping, espionage thriller brings to life the true story of Moe Berg a World War II spy. His mission: go behind enemy lines in Europe to assassinate the Nazi's chief nuclear scientist before the Germans develop an atomic bomb. Berg must rely on his steel-trap intellect in a high-stakes game of cat and mouse - with the fate of the world hanging in the balance.</desc><date>20260718</date><icon src="https://xstreamcp-assets-msp.streamready.in/assets/RUNNTV/PROGRAM/6a5a1b9cb0f02f4dbdefba4d/images/LANDSCAPE_169/a886df06-7b55-4873-bc23-6b9215c02b13.png" /></programme><programme channel="RUNNTV_LIVECHANNEL_7" start="20260718080302 +0000" stop="20260718100838 +0000" catchup-id="RUNNTV_PROGRAM_7_1784361782109_1784369318109"><title>Universal Soldier: Day Of Reckoning</title><desc>John awakens from a coma to discover his wife and daughter were murdered in a brutal home invasion. Haunted by images of the attack, he vows to kill the man responsible: The fight pits John against Andrew Scott and an army of genetically enhanced warriors; meanwhile, he must contend with a Uni Sol in relentless pursuit.</desc><date>20260718</date><icon src="https://xstreamcp-assets-msp.streamready.in/assets/RUNNTV/PROGRAM/6a5a1b9cb0f02f4dbdefba4f/images/LANDSCAPE_169/e836e9d6-f783-4d05-9ae6-da06bde44bcc.png" /></programme><programme channel="RUNNTV_LIVECHANNEL_7" start="20260718100838 +0000" stop="20260718120003 +0000" catchup-id="RUNNTV_PROGRAM_7_1784369318109_1784376003109"><title>Spytime</title><desc>Anacleto, a former secret agent, is forced to come out of retirement and protect his son, Adolfo, when his arch-enemy, Vazquez, breaks out of prison and targets him</desc><date>20260718</date><icon src="https://xstreamcp-assets-msp.streamready.in/assets/RUNNTV/PROGRAM/6a5a1b9cb0f02f4dbdefba51/images/LANDSCAPE_169/dd67a82f-3bbc-4415-80be-a5c3b164bfbd.png" /></programme><programme channel="RUNNTV_LIVECHANNEL_7" start="20260718120003 +0000" stop="20260718134707 +0000" catchup-id="RUNNTV_PROGRAM_7_1784376003109_1784382427109"><title>Haywire</title><desc>From Academy Award-winning director Steven Soderbergh of Ocean&#8217;s 11, 12 &amp; 13 comes HAYWIRE. A Female Assassin covert operative is hired to various global missions to perform jobs which governments can't authorize. When the operation goes awry, she needs to use all of her skills &amp; tricks to escape an international manhunt and eliminate the last remaining link of the conspiracy against her.</desc><date>20260718</date><icon src="https://xstreamcp-assets-msp.streamready.in/assets/RUNNTV/PROGRAM/6a5a1b9cb0f02f4dbdefba53/images/LANDSCAPE_169/fb23382f-d8e4-4fb5-be4f-516af6136659.png" /></programme><channel id="RUNNTV_LIVECHANNEL_10"><display-name>Runn Short Films</display-name><icon src="https://image.airtel.tv/grandslam/content/2025_05_07/LOGO_o7wpa1hH7_R_SFilms-960X540.png" /><lcn>10</lcn></channel><programme channel="RUNNTV_LIVECHANNEL_10" start="20260717000000 +0000" stop="20260719000000 +0000" catchup-id="RUNNTV_PROGRAM_10"><title>Runn Short Films</title><desc /><date>20260717</date><icon src="https://xstreamcp-assets-msp.streamready.in/assets/RUNNTV/LIVECHANNEL/67ed3b4a9555833db945e387/images/LANDSCAPE_169/0b0fc994-5f8a-471f-b1ab-5bd409193d9a.png" /></programme><channel id="RUNNTV_LIVECHANNEL_11"><display-name>Runn Thrillers</display-name><icon src="https://image.airtel.tv/grandslam/content/2025_05_07/LOGO_a08ENfVsZ_R_Thriller-960X540.png" /><lcn>11</lcn></channel><programme channel="RUNNTV_LIVECHANNEL_11" start="20260717000000 +0000" stop="20260719000000 +0000" catchup-id="RUNNTV_PROGRAM_11"><title>Runn Thrillers</title><desc /><date>20260717</date><icon src="https://xstreamcp-assets-msp.streamready.in/assets/RUNNTV/LIVECHANNEL/67ed3b4a9555833db945e385/images/LANDSCAPE_169/45389cac-049d-450b-bb5b-55d1d4aaa08d.png" /></programme><channel id="RUNNTV_LIVECHANNEL_21"><display-name>Runn PrimeTime</display-name><icon src="https://xstreamcp-assets-msp.streamready.in/assets/RUNNTV/LIVECHANNEL/69cfa8b46617185ee1add5fc/images/LOGO/LOGO_COUVCU51O_Runn-PrimeTime_960x540.png" /><lcn>21</lcn></channel><programme channel="RUNNTV_LIVECHANNEL_21" start="20260717000000 +0000" stop="20260719000000 +0000" catchup-id="RUNNTV_PROGRAM_21"><title>Runn PrimeTime</title><desc /><date>20260717</date><icon src="https://xstreamcp-assets-msp.streamready.in/assets/RUNNTV/LIVECHANNEL/69cfa8b46617185ee1add5fc/images/LANDSCAPE_169/2a0ca8c5-2cbf-416d-b5d6-657790baab84.png" /></programme><channel id="RUNNTV_LIVECHANNEL_29"><display-name>Superfine Films</display-name><icon src="https://xstreamcp-assets-msp.streamready.in/assets/RUNNTV/LIVECHANNEL/68e8f234ae2b217a0f92e31c/images/LOGO/LOGO_LxYbOmbng_Superfine-Films-Hindi_960x540.png" /><lcn>29</lcn></channel><programme channel="RUNNTV_LIVECHANNEL_29" start="20260717000000 +0000" stop="20260719000000 +0000" catchup-id="RUNNTV_PROGRAM_29"><title>Superfine Films</title><desc /><date>20260717</date><icon src="https://xstreamcp-assets-msp.streamready.in/assets/RUNNTV/LIVECHANNEL/68e8f234ae2b217a0f92e31c/images/LANDSCAPE_169/17b2cc0e-7c71-4103-9c9e-030ae328377c.png" /></programme><channel id="RUNNTV_LIVECHANNEL_31"><display-name>News Nation</display-name><icon src="https://xstreamcp-assets-msp.streamready.in/assets/RUNNTV/LIVECHANNEL/69e8fa4c02b4b71afa664947/images/LOGO/LOGO_wSv_XG1n5_News-Nation_960x540.png" /><lcn>31</lcn></channel><programme channel="RUNNTV_LIVECHANNEL_31" start="20260717000000 +0000" stop="20260719000000 +0000" catchup-id="RUNNTV_PROGRAM_31"><title>News Nation</title><desc /><date>20260717</date><icon src="https://xstreamcp-assets-msp.streamready.in/assets/RUNNTV/LIVECHANNEL/69e8fa4c02b4b71afa664947/images/LANDSCAPE_169/ce8c726d-d2ab-48f4-bb57-260e2cb6ac8e.png" /></programme><channel id="RUNNTV_LIVECHANNEL_36"><display-name>News State UP/UK</display-name><icon src="https://xstreamcp-assets-msp.streamready.in/assets/RUNNTV/LIVECHANNEL/69e8fa4c02b4b71afa664949/images/LOGO/LOGO_zfIoJqYkH_News-State-UP-UK_960x540.png" /><lcn>36</lcn></channel><programme channel="RUNNTV_LIVECHANNEL_36" start="20260717000000 +0000" stop="20260719000000 +0000" catchup-id="RUNNTV_PROGRAM_36"><title>News State UP/UK</title><desc /><date>20260717</date><icon src="https://xstreamcp-assets-msp.streamready.in/assets/RUNNTV/LIVECHANNEL/69e8fa4c02b4b71afa664949/images/LANDSCAPE_169/4a4184f8-3ae1-4a73-b255-c51cca39377d.jpg" /></programme><channel id="RUNNTV_LIVECHANNEL_39"><display-name>NH BollyGold</display-name><icon src="https://image.airtel.tv/grandslam/content/2025_05_07/NH-BollyGold960X540.png" /><lcn>39</lcn></channel><programme channel="RUNNTV_LIVECHANNEL_39" start="20260717093424 +0000" stop="20260717122043 +0000" catchup-id="RUNNTV_PROGRAM_39_1784280864000_1784290843000"><title>Mohabbat Ki Arzoo</title><desc>A motor mechanic posing as a rich man falls in love with a girl from a wealthy family pretending to be poor. The lovers rebel against their family members and society to remain together.</desc><date>20260717</date><icon src="https://xstreamcp-assets-msp.streamready.in/assets/RUNNTV/PROGRAM/6a5a1b99b0f02f4dbdefba27/images/LANDSCAPE_169/de082e92-b5f6-4490-b631-068f4eef8fab.png" /></programme><programme channel="RUNNTV_LIVECHANNEL_39" start="20260717122043 +0000" stop="20260717145759 +0000" catchup-id="RUNNTV_PROGRAM_39_1784290843000_1784300279000"><title>Param Dharam</title><desc>Savitri believes that her illegitimate child with her deceased lover, Vijay, was stillborn and did not survive. Years later, Savitri's world changes when she learns that her firstborn is alive.</desc><date>20260717</date><icon src="https://xstreamcp-assets-msp.streamready.in/assets/RUNNTV/PROGRAM/6a5a1b99b0f02f4dbdefba2b/images/LANDSCAPE_169/5aaa795e-b9e1-407f-a2ac-c3cbe43ac6af.png" /></programme><programme channel="RUNNTV_LIVECHANNEL_39" start="20260717145759 +0000" stop="20260717174038 +0000" catchup-id="RUNNTV_PROGRAM_39_1784300279000_1784310038000"><title>Andaz</title><desc>Sheetal, a widow, is a school teacher and lives with her son after her husband's death. She meets her student's father Ravi, a widower, and decides to marry him.</desc><date>20260717</date><icon src="https://xstreamcp-assets-msp.streamready.in/assets/RUNNTV/PROGRAM/6a5a1b99b0f02f4dbdefba2b/images/LANDSCAPE_169/5aaa795e-b9e1-407f-a2ac-c3cbe43ac6af.png" /></programme><programme channel="RUNNTV_LIVECHANNEL_39" start="20260717174039 +0000" stop="20260717202108 +0000" catchup-id="RUNNTV_PROGRAM_39_1784310039000_1784319668000"><title>Bhala Manus</title><desc>Shankar a simple villager comes to Bombay in such of work to improve his financial condition but circumstances force him to take up smuggling.</desc><date>20260717</date><icon src="https://xstreamcp-assets-msp.streamready.in/assets/RUNNTV/PROGRAM/6a5a1b9ab0f02f4dbdefba31/images/LANDSCAPE_169/9ae8f176-aab0-4508-abb8-dab106498391.png" /></programme><programme channel="RUNNTV_LIVECHANNEL_39" start="20260717202108 +0000" stop="20260717225824 +0000" catchup-id="RUNNTV_PROGRAM_39_1784319668000_1784329104000"><title>Param Dharam</title><desc>Savitri believes that her illegitimate child with her deceased lover, Vijay, was stillborn and did not survive. Years later, Savitri's world changes when she learns that her firstborn is alive.</desc><date>20260717</date><icon src="https://xstreamcp-assets-msp.streamready.in/assets/RUNNTV/PROGRAM/6a5a1b9ab0f02f4dbdefba35/images/LANDSCAPE_169/5aaa795e-b9e1-407f-a2ac-c3cbe43ac6af.png" /></programme><programme channel="RUNNTV_LIVECHANNEL_39" start="20260717225824 +0000" stop="20260718012025 +0000" catchup-id="RUNNTV_PROGRAM_39_1784329104000_1784337625000"><title>Ram Rajya</title><desc>Lord Rama returns to Ayodhya with his wife Sita after defeating Ravana in an epic battle. However, he exiles his wife when people start doubting her purity.</desc><date>20260717</date><icon src="https://xstreamcp-assets-msp.streamready.in/assets/RUNNTV/PROGRAM/6a5a1b9ab0f02f4dbdefba38/images/LANDSCAPE_169/fa76cb51-9a5e-409f-8ce6-415e0f5f780a.png" /></programme><programme channel="RUNNTV_LIVECHANNEL_39" start="20260718012025 +0000" stop="20260718034403 +0000" catchup-id="RUNNTV_PROGRAM_39_1784337625000_1784346243000"><title>Budkaar</title><desc>Mini, a young woman, is kidnapped from a pub and police investigate the case. However, when her sister sets out to find her, she uncovers a criminal nexus which shakes the city.</desc><date>20260718</date><icon src="https://xstreamcp-assets-msp.streamready.in/assets/RUNNTV/PROGRAM/6a5a1b9ab0f02f4dbdefba3c/images/LANDSCAPE_169/0b0fe4cd-f9a2-4b92-9fe6-bc3eacb4a0e7.png" /></programme><programme channel="RUNNTV_LIVECHANNEL_39" start="20260718034403 +0000" stop="20260718063022 +0000" catchup-id="RUNNTV_PROGRAM_39_1784346243000_1784356222000"><title>Mohabbat Ki Arzoo</title><desc>A motor mechanic posing as a rich man falls in love with a girl from a wealthy family pretending to be poor. The lovers rebel against their family members and society to remain together.</desc><date>20260718</date><icon src="https://xstreamcp-assets-msp.streamready.in/assets/RUNNTV/PROGRAM/6a5a1b9ab0f02f4dbdefba40/images/LANDSCAPE_169/de082e92-b5f6-4490-b631-068f4eef8fab.png" /></programme><programme channel="RUNNTV_LIVECHANNEL_39" start="20260718063023 +0000" stop="20260718091302 +0000" catchup-id="RUNNTV_PROGRAM_39_1784356223000_1784365982000"><title>Andaz</title><desc>Sheetal, a widow, is a school teacher and lives with her son after her husband's death. She meets her student's father Ravi, a widower, and decides to marry him.</desc><date>20260718</date><icon src="https://xstreamcp-assets-msp.streamready.in/assets/RUNNTV/PROGRAM/6a5a1b9ab0f02f4dbdefba40/images/LANDSCAPE_169/de082e92-b5f6-4490-b631-068f4eef8fab.png" /></programme><programme channel="RUNNTV_LIVECHANNEL_39" start="20260718091302 +0000" stop="20260718115508 +0000" catchup-id="RUNNTV_PROGRAM_39_1784365982000_1784375708000"><title>Dushman Duniya Ka</title><desc>Mahesh is a honest and diligent young man, who has no knowledge of his background as he was raised in an orphanage. One day he meets Reshma, who is also an orphan, and both fall in love and get married. They live a harmonious life, and soon are proud parents of a healthy young boy who they name Lucky, who ends up causing them alot of trouble.</desc><date>20260718</date><icon src="https://xstreamcp-assets-msp.streamready.in/assets/RUNNTV/PROGRAM/6a5a1b9bb0f02f4dbdefba49/images/LANDSCAPE_169/250eef87-225d-416d-ad41-b38dbd82e3c7.png" /></programme><programme channel="RUNNTV_LIVECHANNEL_39" start="20260718115509 +0000" stop="20260718143538 +0000" catchup-id="RUNNTV_PROGRAM_39_1784375709000_1784385338000"><title>Bhala Manus</title><desc>Shankar a simple villager comes to Bombay in such of work to improve his financial condition but circumstances force him to take up smuggling.</desc><date>20260718</date><icon src="https://xstreamcp-assets-msp.streamready.in/assets/RUNNTV/PROGRAM/6a5a1b9bb0f02f4dbdefba4c/images/LANDSCAPE_169/9ae8f176-aab0-4508-abb8-dab106498391.png" /></programme><channel id="RUNNTV_LIVECHANNEL_40"><display-name>NH BollyFlix</display-name><icon src="https://image.airtel.tv/grandslam/content/2025_05_07/NH-BollyFlix960X540.png" /><lcn>40</lcn></channel><programme channel="RUNNTV_LIVECHANNEL_40" start="20260717103944 +0000" stop="20260717133438 +0000" catchup-id="RUNNTV_PROGRAM_40_1784284784000_1784295278000"><title>Ilaka (peddupettai)</title><desc>Crime drama about Kumar, a man who rises from a slum to become a powerful figure in the underworld after witnessing his mother's murder. Driven by ambition and vengeance, he navigates betrayal and crime.</desc><date>20260717</date><icon src="https://xstreamcp-assets-msp.streamready.in/assets/RUNNTV/PROGRAM/6a5a1b98b0f02f4dbdefba25/images/LANDSCAPE_169/396083ad-e5c7-409f-8aeb-1e9f3ac4e255.png" /></programme><programme channel="RUNNTV_LIVECHANNEL_40" start="20260717133438 +0000" stop="20260717161701 +0000" catchup-id="RUNNTV_PROGRAM_40_1784295278000_1784305021000"><title>Krantiveer</title><desc>Disowned by his parents at a young age, a man ends up in a small village controlled by underworld dons and powerful politicians. Lazy, alcoholic, and unemployed, he gets influenced by a journalist with a positive mission.</desc><date>20260717</date><icon src="https://xstreamcp-assets-msp.streamready.in/assets/RUNNTV/PROGRAM/6a5a1b99b0f02f4dbdefba26/images/LANDSCAPE_169/be1f16a3-58bb-4486-8bd0-24a05910ed2b.png" /></programme><programme channel="RUNNTV_LIVECHANNEL_40" start="20260717161702 +0000" stop="20260717183536 +0000" catchup-id="RUNNTV_PROGRAM_40_1784305022000_1784313336000"><title>The Shaukeens</title><desc>Bored of their mundane lives, three 60-something men, immersed in the allure of Mauritius, rekindle their youthful spirits and compete for the attention of a vivacious social media addict, Ahana.</desc><date>20260717</date><icon src="https://xstreamcp-assets-msp.streamready.in/assets/RUNNTV/PROGRAM/6a5a1b99b0f02f4dbdefba28/images/LANDSCAPE_169/86d66bcf-b8ec-415c-a768-6885b6540bf6.png" /></programme><programme channel="RUNNTV_LIVECHANNEL_40" start="20260717183536 +0000" stop="20260717210104 +0000" catchup-id="RUNNTV_PROGRAM_40_1784313336000_1784322064000"><title>Patth</title><desc>Summaries. Avi comes from a poor family and lives with his mother and sister, Nandini. He sees that Nandini has befriended a local gangster by the name of Bhullar, and quietly resents this. When Nandini is killed, Avi and two male friends, Golu and Hari, decide to avenge her death - by killing Bhullar.</desc><date>20260717</date><icon src="https://xstreamcp-assets-msp.streamready.in/assets/RUNNTV/PROGRAM/6a5a1b99b0f02f4dbdefba2a/images/LANDSCAPE_169/9103a92a-c340-4079-a37d-cd9b47e95215.jpg" /></programme><programme channel="RUNNTV_LIVECHANNEL_40" start="20260717210104 +0000" stop="20260717233624 +0000" catchup-id="RUNNTV_PROGRAM_40_1784322064000_1784331384000"><title>Tapish</title><desc>The story of Lajwanti, who questions in this era of modernization how much have we actually advanced and how much of it is fake imitation of the west. The story of Lajwanti, who questions in this era of modernization how much have we actually advanced and how much of it is fake imitation of the west.</desc><date>20260717</date><icon src="https://xstreamcp-assets-msp.streamready.in/assets/RUNNTV/PROGRAM/6a5a1b9ab0f02f4dbdefba30/images/LANDSCAPE_169/6c578988-f632-4008-a91a-7baafaa96548.png" /></programme><programme channel="RUNNTV_LIVECHANNEL_40" start="20260717233624 +0000" stop="20260718023118 +0000" catchup-id="RUNNTV_PROGRAM_40_1784331384000_1784341878000"><title>Ilaka (peddupettai)</title><desc>Crime drama about Kumar, a man who rises from a slum to become a powerful figure in the underworld after witnessing his mother's murder. Driven by ambition and vengeance, he navigates betrayal and crime.</desc><date>20260717</date><icon src="https://xstreamcp-assets-msp.streamready.in/assets/RUNNTV/PROGRAM/6a5a1b9ab0f02f4dbdefba34/images/LANDSCAPE_169/396083ad-e5c7-409f-8aeb-1e9f3ac4e255.png" /></programme><programme channel="RUNNTV_LIVECHANNEL_40" start="20260718023118 +0000" stop="20260718041520 +0000" catchup-id="RUNNTV_PROGRAM_40_1784341878000_1784348120000"><title>Toonpur Ka Superr Hero</title><desc>The world is in chaos as there is a constant quarrel between Devtoons, good cartoons, and Toonasurs, bad cartoons. Thereafter, Devtoons decide to abduct Aditya, a superhero, to save them.</desc><date>20260718</date><icon src="https://xstreamcp-assets-msp.streamready.in/assets/RUNNTV/PROGRAM/6a5a1b9ab0f02f4dbdefba36/images/LANDSCAPE_169/13b06cba-bebc-4920-832a-3650336ba4d6.png" /></programme><programme channel="RUNNTV_LIVECHANNEL_40" start="20260718041521 +0000" stop="20260718063355 +0000" catchup-id="RUNNTV_PROGRAM_40_1784348121000_1784356435000"><title>The Shaukeens</title><desc>Bored of their mundane lives, three 60-something men, immersed in the allure of Mauritius, rekindle their youthful spirits and compete for the attention of a vivacious social media addict, Ahana.</desc><date>20260718</date><icon src="https://xstreamcp-assets-msp.streamready.in/assets/RUNNTV/PROGRAM/6a5a1b9ab0f02f4dbdefba3b/images/LANDSCAPE_169/86d66bcf-b8ec-415c-a768-6885b6540bf6.png" /></programme><programme channel="RUNNTV_LIVECHANNEL_40" start="20260718063355 +0000" stop="20260718091618 +0000" catchup-id="RUNNTV_PROGRAM_40_1784356435000_1784366178000"><title>Krantiveer</title><desc>Disowned by his parents at a young age, a man ends up in a small village controlled by underworld dons and powerful politicians. Lazy, alcoholic, and unemployed, he gets influenced by a journalist with a positive mission.</desc><date>20260718</date><icon src="https://xstreamcp-assets-msp.streamready.in/assets/RUNNTV/PROGRAM/6a5a1b9ab0f02f4dbdefba3f/images/LANDSCAPE_169/be1f16a3-58bb-4486-8bd0-24a05910ed2b.png" /></programme><programme channel="RUNNTV_LIVECHANNEL_40" start="20260718091619 +0000" stop="20260718113700 +0000" catchup-id="RUNNTV_PROGRAM_40_1784366179000_1784374620000"><title>C Kkompany</title><desc>A comedy film about three friends who start a fictitious company called C Kkompany to extort money from the corrupt people in their neighborhood. However, their plan backfires when the news of their company spreads like wildfire, and they become the talk of the town. The movie showcases the hilarious consequences of their actions and how they try to redeem themselves in front of the public.</desc><date>20260718</date><icon src="https://xstreamcp-assets-msp.streamready.in/assets/RUNNTV/PROGRAM/6a5a1b9bb0f02f4dbdefba41/images/LANDSCAPE_169/662043e7-6e90-42d2-8ceb-bcd9036b7275.png" /></programme><programme channel="RUNNTV_LIVECHANNEL_40" start="20260718113700 +0000" stop="20260718133704 +0000" catchup-id="RUNNTV_PROGRAM_40_1784374620000_1784381824000"><title>Gali Gali Chor Hai</title><desc>Bharat, a small-time artist, finds himself dealing with the effects of a corrupt system. In the process, he himself discovers his ideals and decides to fight for the rights of the common people.</desc><date>20260718</date><icon src="https://xstreamcp-assets-msp.streamready.in/assets/RUNNTV/PROGRAM/6a5a1b9bb0f02f4dbdefba44/images/LANDSCAPE_169/16e95f37-a9df-4ab5-800d-e42dee64e1c1.jpg" /></programme><channel id="RUNNTV_LIVECHANNEL_41"><display-name>NH BollyRaga</display-name><icon src="https://image.airtel.tv/grandslam/content/2025_05_07/NH-BollyRaga-960X540.png" /><lcn>41</lcn></channel><programme channel="RUNNTV_LIVECHANNEL_41" start="20260717100212 +0000" stop="20260717121859 +0000" catchup-id="RUNNTV_PROGRAM_41_1784282532000_1784290739000"><title>Dance Hits</title><desc>Pure nostalgia on the dance floor! Celebrate the vibrant sounds of old-school Hindi dance music with timeless beats and retro charm.</desc><date>20260717</date><icon src="https://xstreamcp-assets-msp.streamready.in/assets/RUNNTV/PROGRAM/6a5a1b99b0f02f4dbdefba29/images/LANDSCAPE_169/1039f3a5-3673-4a41-b32c-e68234e795a7.png" /></programme><programme channel="RUNNTV_LIVECHANNEL_41" start="20260717121900 +0000" stop="20260717132340 +0000" catchup-id="RUNNTV_PROGRAM_41_1784290740000_1784294620000"><title>Shahenshah Of Bollywood-83rd Birthday Special Vol 2</title><desc>Iconic melodies of Amitabh Bachchan reflecting romance,pride, and cinematic brilliance.</desc><date>20260717</date><icon src="https://xstreamcp-assets-msp.streamready.in/assets/RUNNTV/PROGRAM/6a5a1b99b0f02f4dbdefba2e/images/LANDSCAPE_169/21e433fa-3ddc-4729-baf3-64e6ba4b537f.png" /></programme><programme channel="RUNNTV_LIVECHANNEL_41" start="20260717132341 +0000" stop="20260717152213 +0000" catchup-id="RUNNTV_PROGRAM_41_1784294621000_1784301733000"><title>Zindagi Ka Safar</title><desc>Dive into the emotions of life, with a collection of heartfelt songs that beautifully capture the highs and lows of life. Let these timeless tunes resonate with your emotions and experiences.</desc><date>20260717</date><icon src="https://xstreamcp-assets-msp.streamready.in/assets/RUNNTV/PROGRAM/6a5a1b9ab0f02f4dbdefba33/images/LANDSCAPE_169/e33f8ce5-ba73-4bc3-889f-2f7f1bb9489f.png" /></programme><programme channel="RUNNTV_LIVECHANNEL_41" start="20260717152213 +0000" stop="20260717163339 +0000" catchup-id="RUNNTV_PROGRAM_41_1784301733000_1784306019000"><title>Dilip Kumar &#8211; Tributes To A Legend</title><desc>Celebrate the voice of a generation with songs immortalized by the charisma of Dilip Kumar. Soul-stirring ghazals, patriotic numbers, and emotional ballads that reflect a cinematic titan&#8217;s journey.</desc><date>20260717</date><icon src="https://xstreamcp-assets-msp.streamready.in/assets/RUNNTV/PROGRAM/6a5a1b9ab0f02f4dbdefba39/images/LANDSCAPE_169/21e433fa-3ddc-4729-baf3-64e6ba4b537f.png" /></programme><programme channel="RUNNTV_LIVECHANNEL_41" start="20260717163339 +0000" stop="20260717185400 +0000" catchup-id="RUNNTV_PROGRAM_41_1784306019000_1784314440000"><title>Masti Bhare Geet</title><desc>Feel-good songs to groove to. Perfect for boosting your mood and adding fun to any moment &#8211; pure, carefree energy!</desc><date>20260717</date><icon src="https://xstreamcp-assets-msp.streamready.in/assets/RUNNTV/PROGRAM/6a5a1b9ab0f02f4dbdefba3d/images/LANDSCAPE_169/323fcab5-e40b-42e6-b03d-a9e6e23d55ef.png" /></programme><programme channel="RUNNTV_LIVECHANNEL_41" start="20260717185401 +0000" stop="20260717211113 +0000" catchup-id="RUNNTV_PROGRAM_41_1784314441000_1784322673000"><title>Blissful Beats</title><desc>Soothing melodies that calm your soul. Let these peaceful tunes create your perfect moment of serenity. A carefully curated collection of rhythms to help you unwind.</desc><date>20260717</date><icon src="https://xstreamcp-assets-msp.streamready.in/assets/RUNNTV/PROGRAM/6a5a1b9bb0f02f4dbdefba43/images/LANDSCAPE_169/d0e95475-aa7c-43f5-9f05-41e9c9156bba.png" /></programme><programme channel="RUNNTV_LIVECHANNEL_41" start="20260717211114 +0000" stop="20260717232105 +0000" catchup-id="RUNNTV_PROGRAM_41_1784322674000_1784330465000"><title>Disco Dancer</title><desc>Bring back the flashy disco vibes with this sensational Disco Dancer jukebox. Whether you're a retro lover or a new-age dancer, these beats will keep you moving!</desc><date>20260717</date><icon src="https://xstreamcp-assets-msp.streamready.in/assets/RUNNTV/PROGRAM/6a5a1b9bb0f02f4dbdefba46/images/LANDSCAPE_169/ae5bd272-c1d5-4cb4-871d-e191664dcbb7.png" /></programme><programme channel="RUNNTV_LIVECHANNEL_41" start="20260717232106 +0000" stop="20260718002549 +0000" catchup-id="RUNNTV_PROGRAM_41_1784330466000_1784334349000"><title>Gane Naye Purane</title><desc>Relive the golden era of music with classic melodies, retro rhythms, and timeless tunes that never fade. A nostalgic trip for true old-school lovers!</desc><date>20260717</date><icon src="https://xstreamcp-assets-msp.streamready.in/assets/RUNNTV/PROGRAM/6a5a1b9bb0f02f4dbdefba4b/images/LANDSCAPE_169/0aa714cd-3eb7-49f4-b200-a4834bd833e4.png" /></programme><programme channel="RUNNTV_LIVECHANNEL_41" start="20260718002549 +0000" stop="20260718024045 +0000" catchup-id="RUNNTV_PROGRAM_41_1784334349000_1784342445000"><title>Kumar Sanu Alka Yagnik</title><desc>Fall in love all over again with Kumar Sanu &amp; Alka Yagnik! Their magical duets&#8212;full of passion, heartbreak, and nostalgia&#8212;are pure 90s gold.</desc><date>20260718</date><icon src="https://xstreamcp-assets-msp.streamready.in/assets/RUNNTV/PROGRAM/6a5a1b9cb0f02f4dbdefba4e/images/LANDSCAPE_169/21e433fa-3ddc-4729-baf3-64e6ba4b537f.png" /></programme><programme channel="RUNNTV_LIVECHANNEL_41" start="20260718024046 +0000" stop="20260718051538 +0000" catchup-id="RUNNTV_PROGRAM_41_1784342446000_1784351738000"><title>R D Burman &#8211; Musical Maverick</title><desc>A powerhouse collection of R.D. Burman's iconic hits, blending innovation, emotion, and energy. From soulful ballads to electrifying grooves, experience the genius of Pancham Da that defined Bollywood's golden soundscape.</desc><date>20260718</date><icon src="https://xstreamcp-assets-msp.streamready.in/assets/RUNNTV/PROGRAM/6a5a1b9cb0f02f4dbdefba50/images/LANDSCAPE_169/21e433fa-3ddc-4729-baf3-64e6ba4b537f.png" /></programme><programme channel="RUNNTV_LIVECHANNEL_41" start="20260718051538 +0000" stop="20260718063109 +0000" catchup-id="RUNNTV_PROGRAM_41_1784351738000_1784356269000"><title>Best Of 70s &#8211; The Golden Era</title><desc>Step into Bollywood&#8217;s most soulful decade with this jukebox of evergreen melodies. A rich tapestry of romance, innocence, and timeless charm &#8211; pure nostalgia from the golden 70s.</desc><date>20260718</date><icon src="https://xstreamcp-assets-msp.streamready.in/assets/RUNNTV/PROGRAM/6a5a1b9cb0f02f4dbdefba52/images/LANDSCAPE_169/21e433fa-3ddc-4729-baf3-64e6ba4b537f.png" /></programme><programme channel="RUNNTV_LIVECHANNEL_41" start="20260718063109 +0000" stop="20260718075905 +0000" catchup-id="RUNNTV_PROGRAM_41_1784356269000_1784361545000"><title>Best Of 90s &#8211; Filmy Beats Reloaded</title><desc>Take a ride through the vibrant 90s with peppy love anthems, dramatic duets, and emotional melodies. This jukebox celebrates the signature style of Bollywood's musical revival decade.</desc><date>20260718</date><icon src="https://xstreamcp-assets-msp.streamready.in/assets/RUNNTV/PROGRAM/6a5a1b9cb0f02f4dbdefba54/images/LANDSCAPE_169/21e433fa-3ddc-4729-baf3-64e6ba4b537f.png" /></programme><programme channel="RUNNTV_LIVECHANNEL_41" start="20260718075906 +0000" stop="20260718092426 +0000" catchup-id="RUNNTV_PROGRAM_41_1784361546000_1784366666000"><title>Rajesh Khanna &#8211; The Superstar's Anthems</title><desc>Revisit the unmatched charm of Rajesh Khanna with this jukebox of unforgettable melodies. Romantic, philosophical, and heartfelt &#8211; these songs defined an era and a superstar.</desc><date>20260718</date><icon src="https://xstreamcp-assets-msp.streamready.in/assets/RUNNTV/PROGRAM/6a5a1b9cb0f02f4dbdefba55/images/LANDSCAPE_169/21e433fa-3ddc-4729-baf3-64e6ba4b537f.png" /></programme><programme channel="RUNNTV_LIVECHANNEL_41" start="20260718092426 +0000" stop="20260718105019 +0000" catchup-id="RUNNTV_PROGRAM_41_1784366666000_1784371819000"><title>Jeetendra Hits The Jumping Jack</title><desc>Dive into Jeetendra&#8217;s iconic hits&#8212;The Jumping Jack&#8217;s timeless energy! Relive the magic of Bollywood&#8217;s golden era with foot-tapping beats, romance, and pure nostalgia!</desc><date>20260718</date><icon src="https://xstreamcp-assets-msp.streamready.in/assets/RUNNTV/PROGRAM/6a5a1b9cb0f02f4dbdefba56/images/LANDSCAPE_169/21e433fa-3ddc-4729-baf3-64e6ba4b537f.png" /></programme><programme channel="RUNNTV_LIVECHANNEL_41" start="20260718105020 +0000" stop="20260718120813 +0000" catchup-id="RUNNTV_PROGRAM_41_1784371820000_1784376493000"><title>Neetu Singh Evergreen Hits</title><desc>Turn up the retro vibes with Neetu Singh&#8217;s greatest hits! A birthday playlist packed with nostalgia, romance, and endless charm.</desc><date>20260718</date><icon src="https://xstreamcp-assets-msp.streamready.in/assets/RUNNTV/PROGRAM/6a5a1b9db0f02f4dbdefba57/images/LANDSCAPE_169/21e433fa-3ddc-4729-baf3-64e6ba4b537f.png" /></programme><programme channel="RUNNTV_LIVECHANNEL_41" start="20260718120814 +0000" stop="20260718133259 +0000" catchup-id="RUNNTV_PROGRAM_41_1784376494000_1784381579000"><title>Superhits Of 90s</title><desc>Relive the '90s with Superhits! Romantic melodies, peppy beats, and timeless nostalgia&#8212;dance, sing along, and fall in love all over again!</desc><date>20260718</date><icon src="https://xstreamcp-assets-msp.streamready.in/assets/RUNNTV/PROGRAM/6a5a1b9db0f02f4dbdefba58/images/LANDSCAPE_169/21e433fa-3ddc-4729-baf3-64e6ba4b537f.png" /></programme><channel id="RUNNTV_LIVECHANNEL_94"><display-name>Green Gold TV</display-name><icon src="https://xstreamcp-assets-msp.streamready.in/assets/RUNNTV/LIVECHANNEL/6916c12ef7dcc64622990f83/images/LOGO/LOGO_f_AHbdKaJ_GreenGold_960x540.png" /><lcn>94</lcn></channel><programme channel="RUNNTV_LIVECHANNEL_94" start="20260717000000 +0000" stop="20260719000000 +0000" catchup-id="RUNNTV_PROGRAM_94"><title>Green Gold TV</title><desc /><date>20260717</date><icon src="https://xstreamcp-assets-msp.streamready.in/assets/RUNNTV/LIVECHANNEL/6916c12ef7dcc64622990f83/images/LANDSCAPE_169/9acf6004-e6d8-4b74-a4df-61726b5a3ceb.png" /></programme><channel id="RUNNTV_LIVECHANNEL_95"><display-name>Alright</display-name><icon src="https://xstreamcp-assets-msp.streamready.in/assets/RUNNTV/LIVECHANNEL/6943e9b48cc2e43ace51f51c/images/LOGO/LOGO_mM1TWlAF3_4afd8a30-6f87-47a0-b558-00a8fb70d29c.png" /><lcn>95</lcn></channel><programme channel="RUNNTV_LIVECHANNEL_95" start="20260717000000 +0000" stop="20260719000000 +0000" catchup-id="RUNNTV_PROGRAM_95"><title>Alright</title><desc /><date>20260717</date><icon src="https://xstreamcp-assets-msp.streamready.in/assets/RUNNTV/LIVECHANNEL/6943e9b48cc2e43ace51f51c/images/LANDSCAPE_169/4afd8a30-6f87-47a0-b558-00a8fb70d29c.png" /></programme><channel id="RUNNTV_LIVECHANNEL_120"><display-name>News State Bihar/JH</display-name><icon src="https://xstreamcp-assets-msp.streamready.in/assets/RUNNTV/LIVECHANNEL/69e8fa4d02b4b71afa66494b/images/LOGO/LOGO_Sg9dpZqVF_News-State-Bihar-JH_960x540.png" /><lcn>120</lcn></channel><programme channel="RUNNTV_LIVECHANNEL_120" start="20260717000000 +0000" stop="20260719000000 +0000" catchup-id="RUNNTV_PROGRAM_120"><title>News State Bihar/JH</title><desc /><date>20260717</date><icon src="https://xstreamcp-assets-msp.streamready.in/assets/RUNNTV/LIVECHANNEL/69e8fa4d02b4b71afa66494b/images/LANDSCAPE_169/109d87d8-6ee7-4c98-8e03-5180116429f9.png" /></programme><channel id="RUNNTV_LIVECHANNEL_121"><display-name>News State MP/CG</display-name><icon src="https://xstreamcp-assets-msp.streamready.in/assets/RUNNTV/LIVECHANNEL/69e8fa4d02b4b71afa66494d/images/LOGO/LOGO_-PHLE6H9W_News-State-MP-CG_960x540.png" /><lcn>121</lcn></channel><programme channel="RUNNTV_LIVECHANNEL_121" start="20260717000000 +0000" stop="20260719000000 +0000" catchup-id="RUNNTV_PROGRAM_121"><title>News State MP/CG</title><desc /><date>20260717</date><icon src="https://xstreamcp-assets-msp.streamready.in/assets/RUNNTV/LIVECHANNEL/69e8fa4d02b4b71afa66494d/images/LANDSCAPE_169/6d90a516-75f0-44fe-b7b5-19e17f13b603.png" /></programme><channel id="RUNNTV_LIVECHANNEL_122"><display-name>News State Punjab/HR</display-name><icon src="https://xstreamcp-assets-msp.streamready.in/assets/RUNNTV/LIVECHANNEL/69e8fa4d02b4b71afa66494f/images/LOGO/LOGO_VZ7s7G5lG_News-State-Punjab-HR_960x540.png" /><lcn>122</lcn></channel><programme channel="RUNNTV_LIVECHANNEL_122" start="20260717000000 +0000" stop="20260719000000 +0000" catchup-id="RUNNTV_PROGRAM_122"><title>News State Punjab/HR</title><desc /><date>20260717</date><icon src="https://xstreamcp-assets-msp.streamready.in/assets/RUNNTV/LIVECHANNEL/69e8fa4d02b4b71afa66494f/images/LANDSCAPE_169/3e47a45d-192c-454a-beb2-024f98309d32.png" /></programme><channel id="RUNNTV_LIVECHANNEL_123"><display-name>Eros Universe Bollywood Cinema</display-name><icon src="https://xstreamcp-assets-msp.streamready.in/assets/RUNNTV/LIVECHANNEL/69ef0c811562a47882dbb76e/images/LOGO/LOGO_rfn54SY4o_Eros-Bollywood-Cinema_960x540.png" /><lcn>123</lcn></channel><programme channel="RUNNTV_LIVECHANNEL_123" start="20260717000000 +0000" stop="20260719000000 +0000" catchup-id="RUNNTV_PROGRAM_123"><title>Eros Universe Bollywood Cinema</title><desc /><date>20260717</date><icon src="https://xstreamcp-assets-msp.streamready.in/assets/RUNNTV/LIVECHANNEL/69ef0c811562a47882dbb76e/images/LANDSCAPE_169/29603eac-a495-4ef1-ad50-de64f16d8981.png" /></programme><channel id="RUNNTV_LIVECHANNEL_124"><display-name>Eros Universe Entertainment</display-name><icon src="https://xstreamcp-assets-msp.streamready.in/assets/RUNNTV/LIVECHANNEL/69ef0c821562a47882dbb770/images/LOGO/LOGO_TOtK-3ZmA_Eros-Universe_960x540.png" /><lcn>124</lcn></channel><programme channel="RUNNTV_LIVECHANNEL_124" start="20260717000000 +0000" stop="20260719000000 +0000" catchup-id="RUNNTV_PROGRAM_124"><title>Eros Universe Entertainment</title><desc /><date>20260717</date><icon src="https://xstreamcp-assets-msp.streamready.in/assets/RUNNTV/LIVECHANNEL/69ef0c821562a47882dbb770/images/LANDSCAPE_169/c62534c6-3c2d-4cf7-b7ee-32d2f6fcddaf.png" /></programme><channel id="RUNNTV_LIVECHANNEL_125"><display-name>Mahua Khabar</display-name><icon src="https://xstreamcp-assets-msp.streamready.in/assets/RUNNTV/LIVECHANNEL/69ef0c821562a47882dbb770/images/LOGO/LOGO_TOtK-3ZmA_Eros-Universe_960x540.png" /><lcn>125</lcn></channel><programme channel="RUNNTV_LIVECHANNEL_125" start="20260717000000 +0000" stop="20260719000000 +0000" catchup-id="RUNNTV_PROGRAM_125"><title>Mahua Khabar</title><desc /><date>20260717</date><icon src="https://xstreamcp-assets-msp.streamready.in/assets/RUNNTV/LIVECHANNEL/6a5a16369f820710c1817e9f/images/LANDSCAPE_169/439df44a-760d-4e5e-8bc8-d140308475cc.png" /></programme><channel id="RUNNTV_LIVECHANNEL_126"><display-name>Mahua Play</display-name><icon src="https://xstreamcp-assets-msp.streamready.in/assets/RUNNTV/LIVECHANNEL/69ef0c821562a47882dbb770/images/LOGO/LOGO_TOtK-3ZmA_Eros-Universe_960x540.png" /><lcn>126</lcn></channel><programme channel="RUNNTV_LIVECHANNEL_126" start="20260717000000 +0000" stop="20260719000000 +0000" catchup-id="RUNNTV_PROGRAM_126"><title>Mahua Play</title><desc /><date>20260717</date><icon src="https://xstreamcp-assets-msp.streamready.in/assets/RUNNTV/LIVECHANNEL/6a5a16359f820710c1817e9d/images/LANDSCAPE_169/1ba7b3ea-1426-49ab-838c-bf2171d658e4.png" /></programme></tv>