<tv generator-info-url="https://github.com/amazeyourself/m3u"><channel id="whiplash"><display-name>Whiplash</display-name><icon src="https://whiplash.cc/assets/img/channels/whiplash.png" /></channel><programme channel="whiplash" start="20260529114500 -0400" stop="20260529123000 -0400"><title>Escape to the Country</title><desc>A pair of property hunters have left their wives at home as they go in search of a new rural property to accommodate their extended family in the Wiltshire countryside. Away from the house hunt, Nicki Chapman visits Salisbury Cathedral to learn about its 32-year-old restoration project.</desc><sub-title>Wiltshire</sub-title></programme><channel id="whiplashii"><display-name>Whiplash II</display-name><icon src="https://whiplash.cc/assets/img/channels/whiplash2.png" /></channel><programme channel="whiplashii" start="20260529120031 -0400" stop="20260529135328 -0400"><title>21 Jump Street</title><desc>A pair of underachieving cops are sent back to a local high school to blend in and bring down a synthetic drug ring.</desc><sub-title /></programme><channel id="whiplashcinema"><display-name>Whiplash Cinema</display-name><icon src="https://whiplash.cc/assets/img/channels/whiplashcinema.png" /></channel><programme channel="whiplashcinema" start="20260529114125 -0400" stop="20260529132429 -0400"><title>Moana 2</title><desc>After receiving an unexpected call from her wayfinding ancestors, Moana journeys alongside Maui and a new crew to the far seas of Oceania and into dangerous, long-lost waters for an adventure unlike anything she's ever faced.</desc><sub-title /></programme><channel id="windowtv"><display-name>Window TV</display-name><icon src="https://whiplash.cc/assets/img/channels/windowtv.png" /></channel><programme channel="windowtv" start="20260529170000 +0100" stop="20260529173000 +0100"><title>QI</title><desc>Biscuits, ballet and baboons are on the agenda as Stephen Fry host another edition of the challenging quiz show. Alan Davies, Arthur Smith, Dara O'Briain and Rich Hall are the guests trying to avoid the obvious answers.</desc><sub-title>Biscuits</sub-title></programme><channel id="atlas"><display-name>Atlas</display-name><icon src="https://whiplash.cc/assets/img/channels/atlas.png" /></channel><programme channel="atlas" start="20260529120411 -0400" stop="20260529125623 -0400"><title>MythBusters</title><desc>Adam and Jamie attempt to solve another high calibre conundrum to see if a celebratory gun fire can kill when the bullets fall back to earth. Meanwhile the other members shake their thirst on another round of Vodka myths.</desc><sub-title>Bullets Fired Up</sub-title></programme></tv>